{
  "$schema": "http://json-schema.org/draft-04/schema#",
  "title": "MeasurementResponseData",
  "type": "object",
  "properties": {
    "measurement": {
      "type": "object",
      "properties": {
        "userId": { "type": "string" },
        "measurementId": { "type": "string" },
        "timestamp": { "type": "number" },
        "date": { "type": "string" },
        "note": { "type": "string" },
        "measurements": {
          "type": "object",
          "properties": {
            "weight": { "type": "number" },
            "bodyFatPercentage": { "type": "number" },
            "waterPercentage": { "type": "number" },
            "muscleMassPercentage": { "type": "number" },
            "bonePercentage": { "type": "number" },
            "energyExpenditure": { "type": "number" }
          },
          "required": ["weight"]
        }
      },
      "required": [
        "userId",
        "measurementId",
        "timestamp",
        "date",
        "measurements"
      ]
    }
  },
  "required": ["measurement"]
}
